promethiite/__init__.py
promethiite/__main__.py
promethiite-0.2.0.data/scripts/promethiite
promethiite-0.2.0.dist-info/licenses/LICENSE
promethiite-0.2.0.dist-info/METADATA
promethiite-0.2.0.dist-info/WHEEL
promethiite-0.2.0.dist-info/top_level.txt
promethiite-0.2.0.dist-info/RECORD
