Metadata-Version: 2.4
Name: promethiite
Version: 0.2.0
Summary: Promethiite Ingests Prometheus metrics, converts them to Graphite metrics, and sends them to a configured Graphite server over TCP
Home-page: https://github.com/cspeterson/promethiite
Author: cspeterson
Author-email: contact@cspeterson@net
Project-URL: Documentation, https://github.com/cspeterson/promethiite
Project-URL: Bug Tracker, https://github.com/cspeterson/promethiite/issues
Project-URL: Source, https://github.com/cspeterson/promethiite
Classifier: Programming Language :: Python :: 3
Classifier: License :: OSI Approved :: MIT License
Classifier: Operating System :: OS Independent
Requires-Python: >=3.6
License-File: LICENSE
Requires-Dist: prometheus-client<1.0.0,>=0.20.0
Requires-Dist: graphyte<2.0.0,>=1.7.1
Dynamic: license-file
